wikitablewrapper/__init__.py
wikitablewrapper/aida.py
wikitablewrapper/babelfy.py
wikitablewrapper/freme_ner.py
wikitablewrapper/tagme.py
wikitablewrapper/wikitableBenchmark.py
wikitablewrapper/wikitableWrapper.py
wikitablewrapper-0.2.6.dist-info/LICENSE
wikitablewrapper-0.2.6.dist-info/METADATA
wikitablewrapper-0.2.6.dist-info/WHEEL
wikitablewrapper-0.2.6.dist-info/top_level.txt
wikitablewrapper-0.2.6.dist-info/RECORD
