Metadata-Version: 2.1
Name: wikitablewrapper
Version: 0.2.6
Summary: Parsing, Proccesing, Annotating and Storing WikiTables in Json
Home-page: https://gitlab.com/hrosmendez/wikitablewrapper
Author: Henry Rosales
Author-email: hrosmendez@gmail.com
License: UNKNOWN
Keywords: NIF parser table NLP
Platform: UNKNOWN
Classifier: Development Status :: 3 - Alpha
Classifier: Intended Audience :: Education
Classifier: Topic :: Software Development :: Build Tools
Classifier: License :: OSI Approved :: GNU General Public License v3 (GPLv3)
Classifier: Programming Language :: Python :: 3
Classifier: Programming Language :: Python :: 3.4
Classifier: Programming Language :: Python :: 3.5
Classifier: Programming Language :: Python :: 3.6
Classifier: Programming Language :: Python :: 3.7
Requires-Python: >=2.7, !=3.0.*, !=3.1.*, !=3.2.*, !=3.3.*, <4
Provides-Extra: dev
Requires-Dist: check-manifest ; extra == 'dev'
Provides-Extra: test
Requires-Dist: coverage ; extra == 'test'
